ble_sdk/__init__.py
ble_sdk/client.py
ble_sdk/constants.py
ble_sdk/exceptions.py
ble_sdk/log.py
ble_sdk/scanner.py
ble_sdk/algo/__init__.py
ble_sdk/algo/eeg.py
ble_sdk/algo/impedance.py
ble_sdk/handles/__init__.py
ble_sdk/handles/battery_rssi_handler.py
ble_sdk/handles/eeg_handler.py
ble_sdk/handles/impedance_handler.py
ble_sdk/handles/imu_handler.py
ble_sdk/handles/lead_handler.py
ble_sdk/utils/__init__.py
ble_sdk/utils/cache.py
ble_sdk-1.0.0.dist-info/METADATA
ble_sdk-1.0.0.dist-info/WHEEL
ble_sdk-1.0.0.dist-info/licenses/LICENSE
ble_sdk-1.0.0.dist-info/RECORD
