Metadata-Version: 2.4
Name: ble-sdk
Version: 1.0.0
Summary: Python SDK for BLE IoT devices
Project-URL: Homepage, https://github.com/X-BCI/ble_sdk
Project-URL: Issues, https://github.com/X-BCI/ble_sdk/issues
Author-email: hallexu <25758853@qq.com>
License: MIT
License-File: LICENSE
Classifier: Development Status :: 3 - Alpha
Classifier: Intended Audience :: Developers
Classifier: License :: OSI Approved :: MIT License
Classifier: Programming Language :: Python :: 3
Classifier: Programming Language :: Python :: 3.8
Classifier: Programming Language :: Python :: 3.9
Classifier: Programming Language :: Python :: 3.10
Classifier: Programming Language :: Python :: 3.11
Classifier: Topic :: Software Development :: Libraries :: Python Modules
Classifier: Topic :: System :: Hardware
Requires-Python: >=3.8
Requires-Dist: bleak>=0.22.3
Requires-Dist: loguru>=0.7.3
Requires-Dist: numpy>=1.24.4
Requires-Dist: pytest>=8.3.5
Requires-Dist: scipy>=1.10.1
Provides-Extra: dev
Requires-Dist: black>=23.0.0; extra == 'dev'
Requires-Dist: isort>=5.12.0; extra == 'dev'
Requires-Dist: pytest-asyncio>=0.18.0; extra == 'dev'
Requires-Dist: pytest-cov>=4.1.0; extra == 'dev'
Requires-Dist: pytest>=7.0.0; extra == 'dev'
